highlighter/__init__.py
highlighter/apps.py
highlighter/templatetags/__init__.py
highlighter/templatetags/highlight_yellow.py
dj_search_highlight-0.0.1.dist-info/LICENSE
dj_search_highlight-0.0.1.dist-info/METADATA
dj_search_highlight-0.0.1.dist-info/WHEEL
dj_search_highlight-0.0.1.dist-info/top_level.txt
dj_search_highlight-0.0.1.dist-info/RECORD
